<isomap_predictionfit>
	<job_info>
		<jobkey>66100</jobkey>
		<description>describe this run</description>
		<job_stage>model_prediction</job_stage>
		<model_type>precipitation</model_type>
		<isotope>d2h</isotope>
<formula/>
		<author>caitjcampbell</author>
		
		<access>private</access>
		<tags>
			<tag source="user">killme</tag>
			<tag source="system">ui_testing</tag>
		</tags>
	<template_key stage="model_fitting">66085</template_key></job_info>
	<spatial>
		
		<proj4>+proj=longlat +ellps=wgs84 +datum=wgs84 +no_defs</proj4>
		<upper_longitude>-46.8</upper_longitude>
		<lower_longitude>-177.2</lower_longitude>
		<upper_latitude>76.5</upper_latitude>
		<lower_latitude>6</lower_latitude>
	</spatial>
	<temporal>
		<upper_year>2009</upper_year>
		<lower_year>1980</lower_year>
		<time_mode>synoptic</time_mode>
	<month>1</month><month>2</month><month>3</month><month>4</month><month>5</month><month>6</month><month>7</month><month>8</month><month>9</month><month>10</month><month>11</month><month>12</month></temporal>
	<point_data>
		<locations><station><id>933</id><completeness>100.0</completeness></station><station><id>1086</id><completeness>100.0</completeness></station><station><id>1087</id><completeness>100.0</completeness></station><station><id>1090</id><completeness>98.28559916294604</completeness></station><station><id>10000</id><completeness>100.0</completeness></station><station><id>10001</id><completeness>100.0</completeness></station><station><id>10003</id><completeness>85.78480181344406</completeness></station><station><id>10004</id><completeness>100.0</completeness></station><station><id>10005</id><completeness>99.34589594601586</completeness></station><station><id>10006</id><completeness>82.47947077206132</completeness></station><station><id>10007</id><completeness>100.0</completeness></station><station><id>10008</id><completeness>100.0</completeness></station><station><id>10009</id><completeness>100.0</completeness></station><station><id>10010</id><completeness>100.0</completeness></station><station><id>10011</id><completeness>100.0</completeness></station><station><id>10012</id><completeness>100.0</completeness></station><station><id>10013</id><completeness>100.0</completeness></station><station><id>10014</id><completeness>100.0</completeness></station><station><id>10015</id><completeness>100.0</completeness></station><station><id>10016</id><completeness>100.0</completeness></station><station><id>10017</id><completeness>100.0</completeness></station><station><id>10018</id><completeness>100.0</completeness></station><station><id>10019</id><completeness>100.0</completeness></station><station><id>10020</id><completeness>100.0</completeness></station><station><id>10021</id><completeness>100.0</completeness></station><station><id>10022</id><completeness>100.0</completeness></station><station><id>10023</id><completeness>100.0</completeness></station><station><id>10024</id><completeness>100.0</completeness></station><station><id>10025</id><completeness>100.0</completeness></station><station><id>10026</id><completeness>100.0</completeness></station><station><id>10027</id><completeness>100.0</completeness></station><station><id>10028</id><completeness>100.0</completeness></station><station><id>10029</id><completeness>100.0</completeness></station><station><id>10030</id><completeness>100.0</completeness></station><station><id>10031</id><completeness>100.0</completeness></station><station><id>10032</id><completeness>90.77896815027728</completeness></station><station><id>10033</id><completeness>100.0</completeness></station><station><id>10034</id><completeness>100.0</completeness></station><station><id>10035</id><completeness>100.0</completeness></station><station><id>10036</id><completeness>100.0</completeness></station><station><id>10037</id><completeness>100.0</completeness></station><station><id>10038</id><completeness>98.2585884519856</completeness></station><station><id>10040</id><completeness>100.0</completeness></station><station><id>10041</id><completeness>100.0</completeness></station><station><id>10042</id><completeness>100.0</completeness></station><station><id>10043</id><completeness>82.10841446135564</completeness></station><station><id>10044</id><completeness>100.0</completeness></station><station><id>10045</id><completeness>92.50817079599366</completeness></station><station><id>10046</id><completeness>100.0</completeness></station><station><id>10047</id><completeness>100.0</completeness></station><station><id>10048</id><completeness>100.0</completeness></station><station><id>10049</id><completeness>100.0</completeness></station><station><id>10050</id><completeness>100.0</completeness></station><station><id>10051</id><completeness>100.0</completeness></station><station><id>10052</id><completeness>100.0</completeness></station><station><id>10053</id><completeness>100.0</completeness></station><station><id>10054</id><completeness>100.0</completeness></station><station><id>10055</id><completeness>100.0</completeness></station><station><id>10057</id><completeness>100.0</completeness></station><station><id>10058</id><completeness>98.48050596429428</completeness></station><station><id>10059</id><completeness>98.420214150159</completeness></station><station><id>10060</id><completeness>100.0</completeness></station><station><id>10061</id><completeness>100.0</completeness></station><station><id>10062</id><completeness>100.0</completeness></station><station><id>10063</id><completeness>100.0</completeness></station><station><id>10064</id><completeness>100.0</completeness></station><station><id>10065</id><completeness>100.0</completeness></station><station><id>10066</id><completeness>100.0</completeness></station><station><id>10067</id><completeness>100.0</completeness></station><station><id>10068</id><completeness>100.0</completeness></station><station><id>10069</id><completeness>100.0</completeness></station><station><id>10070</id><completeness>100.0</completeness></station><station><id>10071</id><completeness>100.0</completeness></station><station><id>10072</id><completeness>100.0</completeness></station><station><id>10073</id><completeness>100.0</completeness></station><station><id>10074</id><completeness>100.0</completeness></station><station><id>10075</id><completeness>100.0</completeness></station><station><id>10076</id><completeness>100.0</completeness></station><station><id>7107200</id><completeness>100.0</completeness></station><station><id>7108100</id><completeness>100.0</completeness></station><station><id>7108101</id><completeness>100.0</completeness></station><station><id>7139800</id><completeness>100.0</completeness></station><station><id>7152700</id><completeness>80.8823629195872</completeness></station><station><id>7162800</id><completeness>100.0</completeness></station><station><id>7172000</id><completeness>100.0</completeness></station><station><id>7174800</id><completeness>96.03775063338526</completeness></station><station><id>7179900</id><completeness>82.1876814709232</completeness></station><station><id>7185600</id><completeness>100.0</completeness></station><station><id>7186500</id><completeness>100.0</completeness></station><station><id>7186700</id><completeness>100.0</completeness></station><station><id>7187701</id><completeness>100.0</completeness></station><station><id>7191300</id><completeness>100.0</completeness></station><station><id>7192400</id><completeness>100.0</completeness></station><station><id>7192500</id><completeness>100.0</completeness></station><station><id>7193401</id><completeness>100.0</completeness></station><station><id>7195700</id><completeness>90.29548567729896</completeness></station><station><id>7196400</id><completeness>100.0</completeness></station><station><id>7196401</id><completeness>100.0</completeness></station><station><id>7222861</id><completeness>100.0</completeness></station><station><id>7622500</id><completeness>100.0</completeness></station><station><id>7669200</id><completeness>100.0</completeness></station><station><id>7831501</id><completeness>91.9177192816264</completeness></station><station><id>7831502</id><completeness>89.54588997819131</completeness></station><station><id>7831701</id><completeness>89.0852557949415</completeness></station><station><id>7832501</id><completeness>100.0</completeness></station><station><id>7833200</id><completeness>96.8640661630941</completeness></station><station><id>7833301</id><completeness>85.75610022232227</completeness></station><station><id>7837401</id><completeness>100.0</completeness></station><station><id>7848601</id><completeness>100.0</completeness></station><station><id>7866300</id><completeness>94.65271115545494</completeness></station><station><id>7870801</id><completeness>96.4888428647782</completeness></station><station><id>7870802</id><completeness>96.4888428647782</completeness></station><station><id>7872801</id><completeness>86.95529566072793</completeness></station><station><id>7872802</id><completeness>86.95529566072793</completeness></station><station><id>7872803</id><completeness>92.0992458192152</completeness></station><station><id>7875501</id><completeness>85.13590632006077</completeness></station><station><id>7875502</id><completeness>98.97929873670151</completeness></station><station><id>7875503</id><completeness>99.29356773874069</completeness></station><station><id>7876000</id><completeness>98.63133255039497</completeness></station><station><id>7876001</id><completeness>91.28677444075672</completeness></station><station><id>7876002</id><completeness>98.55612220273817</completeness></station><station><id>7876052</id><completeness>94.90755186823543</completeness></station><station><id>7876201</id><completeness>100.0</completeness></station><station><id>7876204</id><completeness>82.96477444195848</completeness></station><station><id>7877200</id><completeness>87.16894275320921</completeness></station><station><id>7877401</id><completeness>92.25899093957867</completeness></station><station><id>7877402</id><completeness>99.37206253306447</completeness></station><station><id>7877403</id><completeness>96.9494609698786</completeness></station><station><id>7880600</id><completeness>100.0</completeness></station><station><id>7880602</id><completeness>100.0</completeness></station><station><id>7895400</id><completeness>100.0</completeness></station><station><id>8002800</id><completeness>98.70906820567936</completeness></station><station><id>8004401</id><completeness>100.0</completeness></station><station><id>8009101</id><completeness>100.0</completeness></station><station><id>8009301</id><completeness>100.0</completeness></station><station><id>8009303</id><completeness>82.40715209463632</completeness></station><station><id>8009304</id><completeness>82.40715209463632</completeness></station><station><id>8009402</id><completeness>82.40715209463632</completeness></station><station><id>8009501</id><completeness>88.3472611241596</completeness></station><station><id>8009502</id><completeness>100.0</completeness></station><station><id>8009503</id><completeness>97.03386506577824</completeness></station><station><id>933</id><completeness>100.0</completeness></station><station><id>1086</id><completeness>100.0</completeness></station><station><id>1087</id><completeness>100.0</completeness></station><station><id>1090</id><completeness>98.28559916294604</completeness></station><station><id>10000</id><completeness>100.0</completeness></station><station><id>10001</id><completeness>100.0</completeness></station><station><id>10003</id><completeness>85.7848018134441</completeness></station><station><id>10004</id><completeness>100.0</completeness></station><station><id>10005</id><completeness>99.34589594601586</completeness></station><station><id>10006</id><completeness>82.47947077206132</completeness></station><station><id>10007</id><completeness>100.0</completeness></station><station><id>10008</id><completeness>100.0</completeness></station><station><id>10009</id><completeness>100.0</completeness></station><station><id>10010</id><completeness>100.0</completeness></station><station><id>10011</id><completeness>100.0</completeness></station><station><id>10012</id><completeness>100.0</completeness></station><station><id>10013</id><completeness>100.0</completeness></station><station><id>10014</id><completeness>100.0</completeness></station><station><id>10015</id><completeness>100.0</completeness></station><station><id>10016</id><completeness>100.0</completeness></station><station><id>10017</id><completeness>100.0</completeness></station><station><id>10018</id><completeness>100.0</completeness></station><station><id>10019</id><completeness>100.0</completeness></station><station><id>10020</id><completeness>100.0</completeness></station><station><id>10021</id><completeness>100.0</completeness></station><station><id>10022</id><completeness>100.0</completeness></station><station><id>10023</id><completeness>100.0</completeness></station><station><id>10024</id><completeness>100.0</completeness></station><station><id>10025</id><completeness>100.0</completeness></station><station><id>10026</id><completeness>100.0</completeness></station><station><id>10027</id><completeness>100.0</completeness></station><station><id>10028</id><completeness>100.0</completeness></station><station><id>10029</id><completeness>100.0</completeness></station><station><id>10030</id><completeness>100.0</completeness></station><station><id>10031</id><completeness>100.0</completeness></station><station><id>10032</id><completeness>90.77896815027728</completeness></station><station><id>10033</id><completeness>100.0</completeness></station><station><id>10034</id><completeness>100.0</completeness></station><station><id>10035</id><completeness>100.0</completeness></station><station><id>10036</id><completeness>100.0</completeness></station><station><id>10037</id><completeness>100.0</completeness></station><station><id>10038</id><completeness>98.2585884519856</completeness></station><station><id>10040</id><completeness>100.0</completeness></station><station><id>10041</id><completeness>100.0</completeness></station><station><id>10042</id><completeness>100.0</completeness></station><station><id>10043</id><completeness>82.10841446135564</completeness></station><station><id>10044</id><completeness>100.0</completeness></station><station><id>10045</id><completeness>92.50817079599366</completeness></station><station><id>10046</id><completeness>100.0</completeness></station><station><id>10047</id><completeness>100.0</completeness></station><station><id>10048</id><completeness>100.0</completeness></station><station><id>10049</id><completeness>100.0</completeness></station><station><id>10050</id><completeness>100.0</completeness></station><station><id>10051</id><completeness>100.0</completeness></station><station><id>10052</id><completeness>100.0</completeness></station><station><id>10053</id><completeness>100.0</completeness></station><station><id>10054</id><completeness>100.0</completeness></station><station><id>10055</id><completeness>100.0</completeness></station><station><id>10057</id><completeness>100.0</completeness></station><station><id>10058</id><completeness>98.48050596429428</completeness></station><station><id>10059</id><completeness>98.420214150159</completeness></station><station><id>10060</id><completeness>100.0</completeness></station><station><id>10061</id><completeness>100.0</completeness></station><station><id>10062</id><completeness>100.0</completeness></station><station><id>10063</id><completeness>100.0</completeness></station><station><id>10064</id><completeness>100.0</completeness></station><station><id>10065</id><completeness>100.0</completeness></station><station><id>10066</id><completeness>100.0</completeness></station><station><id>10067</id><completeness>100.0</completeness></station><station><id>10068</id><completeness>100.0</completeness></station><station><id>10069</id><completeness>100.0</completeness></station><station><id>10070</id><completeness>100.0</completeness></station><station><id>10071</id><completeness>100.0</completeness></station><station><id>10072</id><completeness>100.0</completeness></station><station><id>10073</id><completeness>100.0</completeness></station><station><id>10074</id><completeness>100.0</completeness></station><station><id>10075</id><completeness>100.0</completeness></station><station><id>10076</id><completeness>100.0</completeness></station><station><id>7107200</id><completeness>100.0</completeness></station><station><id>7108100</id><completeness>100.0</completeness></station><station><id>7108101</id><completeness>100.0</completeness></station><station><id>7139800</id><completeness>100.0</completeness></station><station><id>7152700</id><completeness>80.8823629195872</completeness></station><station><id>7162800</id><completeness>100.0</completeness></station><station><id>7172000</id><completeness>100.0</completeness></station><station><id>7174800</id><completeness>96.03775063338526</completeness></station><station><id>7179900</id><completeness>82.1876814709232</completeness></station><station><id>7185600</id><completeness>100.0</completeness></station><station><id>7186500</id><completeness>100.0</completeness></station><station><id>7186700</id><completeness>100.0</completeness></station><station><id>7187701</id><completeness>100.0</completeness></station><station><id>7191300</id><completeness>100.0</completeness></station><station><id>7192400</id><completeness>100.0</completeness></station><station><id>7192500</id><completeness>100.0</completeness></station><station><id>7193401</id><completeness>100.0</completeness></station><station><id>7195700</id><completeness>90.29548567729896</completeness></station><station><id>7196400</id><completeness>100.0</completeness></station><station><id>7196401</id><completeness>100.0</completeness></station><station><id>7222861</id><completeness>100.0</completeness></station><station><id>7622500</id><completeness>100.0</completeness></station><station><id>7669200</id><completeness>100.0</completeness></station><station><id>7831501</id><completeness>91.9177192816264</completeness></station><station><id>7831502</id><completeness>89.54588997819131</completeness></station><station><id>7831701</id><completeness>89.0852557949415</completeness></station><station><id>7832501</id><completeness>100.0</completeness></station><station><id>7833200</id><completeness>96.8640661630941</completeness></station><station><id>7833301</id><completeness>85.75610022232227</completeness></station><station><id>7837401</id><completeness>100.0</completeness></station><station><id>7848601</id><completeness>100.0</completeness></station><station><id>7866300</id><completeness>94.65271115545494</completeness></station><station><id>7870801</id><completeness>96.4888428647782</completeness></station><station><id>7870802</id><completeness>96.4888428647782</completeness></station><station><id>7872801</id><completeness>86.95529566072793</completeness></station><station><id>7872802</id><completeness>86.95529566072793</completeness></station><station><id>7872803</id><completeness>92.0992458192152</completeness></station><station><id>7875501</id><completeness>85.13590632006077</completeness></station><station><id>7875502</id><completeness>98.97929873670151</completeness></station><station><id>7875503</id><completeness>99.29356773874069</completeness></station><station><id>7876000</id><completeness>98.63133255039497</completeness></station><station><id>7876001</id><completeness>91.28677444075672</completeness></station><station><id>7876002</id><completeness>98.55612220273817</completeness></station><station><id>7876052</id><completeness>94.90755186823543</completeness></station><station><id>7876201</id><completeness>100.0</completeness></station><station><id>7876204</id><completeness>82.96477444195848</completeness></station><station><id>7877200</id><completeness>87.16894275320921</completeness></station><station><id>7877401</id><completeness>92.25899093957867</completeness></station><station><id>7877402</id><completeness>99.37206253306447</completeness></station><station><id>7877403</id><completeness>96.9494609698786</completeness></station><station><id>7880600</id><completeness>100.0</completeness></station><station><id>7880602</id><completeness>100.0</completeness></station><station><id>7895400</id><completeness>100.0</completeness></station><station><id>8002800</id><completeness>98.70906820567936</completeness></station><station><id>8004401</id><completeness>100.0</completeness></station><station><id>8009101</id><completeness>100.0</completeness></station><station><id>8009301</id><completeness>100.0</completeness></station><station><id>8009303</id><completeness>82.40715209463632</completeness></station><station><id>8009304</id><completeness>82.40715209463632</completeness></station><station><id>8009402</id><completeness>82.40715209463632</completeness></station><station><id>8009501</id><completeness>88.3472611241596</completeness></station><station><id>8009502</id><completeness>100.0</completeness></station><station><id>8009503</id><completeness>97.03386506577824</completeness></station></locations>
		<variables><variable type="dependent"><name value="d2h"><name_full>d2h</name_full></name><data_source field="d2h" obs_header="d2h" table="inpoint_data_new"/></variable><variable type="independent"><name value="pre"><name_full>precipitation</name_full></name><data_source field="pre" obs_header="pre_p" table="inpoint_data_new" transform="p"/></variable><variable type="independent"><name value="elev"><name_full>elevation</name_full></name><data_source field="elev" obs_header="elev_e" table="inpoint_stations_new" transform="e"/></variable><variable type="independent"><name value="lat"><name_full>latitudesquared</name_full></name><data_source field="st_y(geom)" obs_header="lat_l^2" table="inpoint_stations_new" transform="l^2"/></variable><variable type="independent"><name value="lon"><name_full>longitudesquared</name_full></name><data_source field="st_x(geom)" obs_header="lon_l^2" table="inpoint_stations_new" transform="l^2"/></variable></variables>
		<extraction_process>
			<db>
				<name>isomap_dev</name>
				<version>2.0</version>
			</db>
			<extraction>
				
				<date/>
				<filename/>
			</extraction>
		</extraction_process>
	</point_data>
	<raster_data>
		
	<variables><variable type="dependent"><name value="d2h"><name_full>d2h</name_full></name><data_source field="d2h" obs_header="d2h" table="inpoint_data_new"/></variable><variable type="independent"><name value="pre"><name_full>precipitation </name_full></name><data_source field="pre" obs_header="pre_p" table="cru" transform="p"/></variable><variable type="independent"><name value="elev"><name_full>elevation </name_full></name><data_source field="elev" obs_header="elev_e" table="etopo" transform="e"/></variable><variable type="independent"><name value="lat"><name_full>latitude squared</name_full></name><data_source field="st_y(geom)" obs_header="lat_l^2" table="grid" transform="l^2"/></variable><variable type="independent"><name value="lon"><name_full>longitude squared</name_full></name><data_source field="st_x(geom)" obs_header="lon_l^2" table="grid" transform="l^2"/></variable></variables></raster_data>
	<submission_status>
		<casename>Annual_NoAm_Map_H_1980_2010</casename>
		<timestamp>Wed Jan 24 12:43:08 EST 2018</timestamp>
		<globus_version>comment_check</globus_version>
	</submission_status>
	<runtime_info>
		<status>comment_check</status>
		<resource/>
		<job_scheduler>jobmanager-pbs</job_scheduler>
		<job_queue>isomap</job_queue>
		<run_time unit="min"/>
		<wait_time unit="min"/>
	</runtime_info>
	<output>
		<directorypath>/depot/ssg/isomap/data/isomap-prod/portal/caitjcampbell/jobs/66085</directorypath>
		<regression_model>
			<mse>302.556</mse>
			<determination_coefficient>0.839709</determination_coefficient>
			<ivalue>0.484242</ivalue>
			<pvalue>2.51259e-10</pvalue>
		</regression_model>
		<geostatistical_model>
			<mse>409.51</mse>
		</geostatistical_model>
	</output>
</isomap_predictionfit>